audio_case_grade/__init__.py
audio_case_grade/clean.py
audio_case_grade/core.py
audio_case_grade/keybank.py
audio_case_grade/keyword.py
audio_case_grade/language.py
audio_case_grade/proficiency.py
audio_case_grade/py.typed
audio_case_grade/types.py
audio_case_grade/resources/__init__.py
audio_case_grade/resources/abbreviations.csv
audio_case_grade/resources/keybank.csv
audio_case_grade/resources/nltk/corpora/stopwords.zip
audio_case_grade/resources/nltk/corpora/wordnet.zip
audio_case_grade/resources/nltk/corpora/stopwords/README
audio_case_grade/resources/nltk/corpora/stopwords/arabic
audio_case_grade/resources/nltk/corpora/stopwords/azerbaijani
audio_case_grade/resources/nltk/corpora/stopwords/basque
audio_case_grade/resources/nltk/corpora/stopwords/bengali
audio_case_grade/resources/nltk/corpora/stopwords/catalan
audio_case_grade/resources/nltk/corpora/stopwords/chinese
audio_case_grade/resources/nltk/corpora/stopwords/danish
audio_case_grade/resources/nltk/corpora/stopwords/dutch
audio_case_grade/resources/nltk/corpora/stopwords/english
audio_case_grade/resources/nltk/corpora/stopwords/finnish
audio_case_grade/resources/nltk/corpora/stopwords/french
audio_case_grade/resources/nltk/corpora/stopwords/german
audio_case_grade/resources/nltk/corpora/stopwords/greek
audio_case_grade/resources/nltk/corpora/stopwords/hebrew
audio_case_grade/resources/nltk/corpora/stopwords/hinglish
audio_case_grade/resources/nltk/corpora/stopwords/hungarian
audio_case_grade/resources/nltk/corpora/stopwords/indonesian
audio_case_grade/resources/nltk/corpora/stopwords/italian
audio_case_grade/resources/nltk/corpora/stopwords/kazakh
audio_case_grade/resources/nltk/corpora/stopwords/nepali
audio_case_grade/resources/nltk/corpora/stopwords/norwegian
audio_case_grade/resources/nltk/corpora/stopwords/portuguese
audio_case_grade/resources/nltk/corpora/stopwords/romanian
audio_case_grade/resources/nltk/corpora/stopwords/russian
audio_case_grade/resources/nltk/corpora/stopwords/slovene
audio_case_grade-0.2.3.dist-info/METADATA
audio_case_grade-0.2.3.dist-info/WHEEL
audio_case_grade-0.2.3.dist-info/RECORD
