Metadata-Version: 2.4
Name: audio-case-grade
Version: 0.2.3
Summary: Library to score audio medical case studies
Author-email: Taylor Daniels <tdaniels@vcom.edu>, Keith Fung <keith.fung@infernored.com>
Classifier: Development Status :: 4 - Beta
Classifier: Intended Audience :: Developers
Classifier: Intended Audience :: Education
Classifier: Intended Audience :: Healthcare Industry
Classifier: Intended Audience :: Science/Research
Classifier: Operating System :: OS Independent
Classifier: Programming Language :: Python :: 3
Classifier: Programming Language :: Python :: 3.9
Classifier: Programming Language :: Python :: 3.10
Classifier: Programming Language :: Python :: 3.11
Classifier: Programming Language :: Python :: 3.12
Classifier: Programming Language :: Python :: 3.13
Requires-Python: <3.14,>=3.9
Requires-Dist: jiwer>=3.0.5
Requires-Dist: nltk>=3.9.1
Requires-Dist: num2words>=0.5.13
Requires-Dist: numpy<2.0.0,>=1.21.0; python_version < '3.13'
Requires-Dist: numpy>=2.1.3; python_version >= '3.13'
Requires-Dist: pandas-stubs<2.3.0,>=2.0.0
Requires-Dist: pandas<2.3.0,>=1.3.0
Requires-Dist: pydantic<3.0.0,>=2.0.0
